README.md
setup.py
ommtk/__init__.py
ommtk/build_CVs.py
ommtk/custom_reporters.py
ommtk/ommtk.py
ommtk/segment_walk_metaD.py
ommtk/utils.py
ommtk.egg-info/PKG-INFO
ommtk.egg-info/SOURCES.txt
ommtk.egg-info/dependency_links.txt
ommtk.egg-info/top_level.txt
ommtk/runtime/__init__.py
ommtk/runtime/md-launch-equil.py
ommtk/runtime/md-launch-npt.py
ommtk/runtime/min.py