Metadata-Version: 2.1
Name: ommtk
Version: 0.3.10
Summary: OpenMM Toolkit by Redesign Science
Home-page: https://github.com/RedesignScience/OMMTK
Author: Gavin Bascom, Haotian Li, Janan Zhu
Author-email: gavin@redesignscience.com
License: UNKNOWN
Platform: UNKNOWN
Classifier: Programming Language :: Python :: 3
Classifier: License :: OSI Approved :: MIT License
Classifier: Operating System :: OS Independent
Requires-Python: >=3.6
